Metadata-Version: 2.4
Name: vantage6_client
Version: 4.13.6
Summary: Vantage6 client
Home-page: https://github.com/vantage6/vantage6
Requires-Python: >=3.10
Requires-Dist: pyjwt==2.9.0
Requires-Dist: pyfiglet==1.0.4
Requires-Dist: vantage6-common==4.13.6
Provides-Extra: dev
Requires-Dist: black; extra == "dev"
Requires-Dist: pre-commit; extra == "dev"
Dynamic: description
Dynamic: description-content-type
Dynamic: home-page
Dynamic: provides-extra
Dynamic: requires-dist
Dynamic: requires-python
Dynamic: summary
